fsetools/__init__.py
fsetools/etc/asciiplot.py
fsetools/etc/latex.py
fsetools/etc/safir.py
fsetools/etc/transforms2d.py
fsetools/etc/util.py
fsetools/lib/__init__.py
fsetools/lib/asciiplot.py
fsetools/lib/fse_activation_hd.py
fsetools/lib/fse_bs_en_1991_1_2_external_flame.py
fsetools/lib/fse_bs_en_1991_1_2_external_flame_forced_draught.py
fsetools/lib/fse_bs_en_1991_1_2_parametric_fire.py
fsetools/lib/fse_bs_en_1993_1_2_external_beam.py
fsetools/lib/fse_bs_en_1993_1_2_external_column.py
fsetools/lib/fse_bs_en_1993_1_2_heat_transfer.py
fsetools/lib/fse_bs_en_1993_1_2_heat_transfer_c.c
fsetools/lib/fse_bs_en_1993_1_2_heat_transfer_c.cp37-win_amd64.pyd
fsetools/lib/fse_din_en_1991_1_2_parametric_fire.py
fsetools/lib/fse_escape_past_cooker.py
fsetools/lib/fse_eurocode_external_steel.py
fsetools/lib/fse_flame_height.py
fsetools/lib/fse_latex_report_template.py
fsetools/lib/fse_thermal_radiation.py
fsetools/lib/fse_thermal_radiation_2d.py
fsetools/lib/fse_thermal_radiation_2d_ortho.py
fsetools/lib/fse_thermal_radiation_2d_parallel.py
fsetools/lib/fse_thermal_radiation_2d_perpendicular.py
fsetools/lib/fse_thermal_radiation_2d_v2.py
fsetools/lib/fse_thermal_radiation_3d.py
fsetools/lib/fse_travelling_fire.py
fsetools/lib/fse_travelling_fire_flux.py
fsetools/lib/heat_transfer_unprotected_steel_ec.py
fsetools/libstd/__init__.py
fsetools/libstd/bre_br_187_2014.py
fsetools/libstd/bs_9999_2017.py
fsetools/libstd/bs_en_1991_1_2_2002_annex_a.py
fsetools/libstd/bs_en_1991_1_2_2002_annex_a_wip.py
fsetools/libstd/bs_en_1991_1_2_2002_annex_b.py
fsetools/libstd/bs_en_1991_1_2_2002_annex_e.py
fsetools/libstd/bs_en_1991_1_2_2002_annex_g.py
fsetools/libstd/bs_en_1993_1_2_2005_annex_b.py
fsetools/libstd/ec_1991_1_2.py
fsetools/libstd/fire_iso834.py
fsetools/libstd/iso_834.py
fsetools/libstd/nist_sp_1019_2019.py
fsetools/libstd/pd_7974_1_2019.py
fsetools-0.0.5.dist-info/LICENSE
fsetools-0.0.5.dist-info/METADATA
fsetools-0.0.5.dist-info/WHEEL
fsetools-0.0.5.dist-info/top_level.txt
fsetools-0.0.5.dist-info/RECORD
