Metadata-Version: 2.1
Name: fsetools
Version: 0.0.5
Summary: Fire Safety Engineering Tools
Home-page: https://github.com/fsepy/fsetools
Author: Ian Fu
Author-email: fuyans@gmail.com
License: UNKNOWN
Download-URL: https://github.com/fsepy/fsetools/archive/master.zip
Keywords: fire,safety,engineering
Platform: UNKNOWN
Classifier: Programming Language :: Python :: 3
Classifier: Development Status :: 4 - Beta
Classifier: Environment :: Other Environment
Classifier: Intended Audience :: Developers
Classifier: License :: OSI Approved :: Apache Software License
Classifier: Operating System :: OS Independent
Classifier: Topic :: Scientific/Engineering
Requires-Dist: numpy (>=1.18.1)
Requires-Dist: docopt (>=0.6.2)
Requires-Dist: packaging (>=20.1)
Requires-Dist: matplotlib (<=3.2.2)
Requires-Dist: scipy (>=1.5.0)
Requires-Dist: pylatex (>=1.4.0)
